h3_toolkit/__init__.py
h3_toolkit/aggregation.py
h3_toolkit/core.py
h3_toolkit/exceptions.py
h3_toolkit/hbase.py
h3_toolkit/utils.py
h3_toolkit-0.3.12.dist-info/METADATA
h3_toolkit-0.3.12.dist-info/WHEEL
h3_toolkit-0.3.12.dist-info/RECORD
