Metadata-Version: 2.3
Name: h3-toolkit
Version: 0.3.12
Summary: 
Author: Huang SyuanBo
Author-email: godspeed88168@gmail.com
Requires-Python: >=3.10.12,<4.0.0
Classifier: Programming Language :: Python :: 3
Classifier: Programming Language :: Python :: 3.11
Classifier: Programming Language :: Python :: 3.12
Classifier: Programming Language :: Python :: 3.13
Requires-Dist: aiohttp (>=3.11.14,<4.0.0)
Requires-Dist: geopandas (>=1.0.1,<2.0.0)
Requires-Dist: h3ronpy (>=0.21.0,<0.22.0)
Requires-Dist: polars (==1.2.1)
Requires-Dist: tqdm (>=4.66.5,<5.0.0)
